Metadata-Version: 1.0
Name: skakdollar
Version: 0.1.3
Summary: The funniest joke in the world
Home-page: http://github.com/killall5/skakdollar
Author: Alexey Tamarevskiy
Author-email: killall5@me.com
License: MIT
Platform: UNKNOWN
